smi_analysis/Detector.py
smi_analysis/SMI_beamline.py
smi_analysis/SMI_test.py
smi_analysis/__init__.py
smi_analysis/_version.py
smi_analysis/databroker_interaction.py
smi_analysis/export.py
smi_analysis/integrate1D.py
smi_analysis/remesh.py
smi_analysis/stitch.py
smi_analysis/tests/__init__.py
smi_analysis/tests/conftest.py
smi_analysis/tests/test_pygix_transform.py
smi_analysis-0.2.2.dist-info/licenses/AUTHORS.rst
smi_analysis-0.2.2.dist-info/licenses/LICENSE
smi_analysis-0.2.2.dist-info/METADATA
smi_analysis-0.2.2.dist-info/WHEEL
smi_analysis-0.2.2.dist-info/top_level.txt
smi_analysis-0.2.2.dist-info/RECORD
