Metadata-Version: 2.4
Name: smi-analysis
Version: 0.2.2
Summary: Scientific Python for data analysis at the Soft Matter Interface (SMI) beamline at NSLS-II
Home-page: https://github.com/NSLS-II-SMI/smi-analysis
Author: Brokhaven National Laboratory
Author-email: gfreychet@gmail.com
License: BSD-3-Clause
Classifier: Development Status :: 2 - Pre-Alpha
Classifier: Natural Language :: English
Classifier: Programming Language :: Python :: 3
Requires-Python: >=3.9
License-File: LICENSE
License-File: AUTHORS.rst
Requires-Dist: h5py
Requires-Dist: numpy
Requires-Dist: pyFAI
Requires-Dist: pygix>=2022.11.14
Requires-Dist: scipy
Requires-Dist: xarray
Dynamic: author
Dynamic: author-email
Dynamic: classifier
Dynamic: description
Dynamic: description-content-type
Dynamic: home-page
Dynamic: license
Dynamic: license-file
Dynamic: requires-dist
Dynamic: requires-python
Dynamic: summary
